setup.py
soundac/__init__.py
soundac.egg-info/PKG-INFO
soundac.egg-info/SOURCES.txt
soundac.egg-info/dependency_links.txt
soundac.egg-info/top_level.txt